peconfigurator/asimov.py
peconfigurator/asimov_template.yaml
peconfigurator/get_settings.py
peconfigurator/proc_samples.py
peconfigurator/run_on_many_events.py
peconfigurator/auxiliary/__init__.py
peconfigurator/auxiliary/make_report.py
peconfigurator/auxiliary/plotting.py
peconfigurator/auxiliary/produce_fake_posteriors.ipynb
peconfigurator/auxiliary/run_analyzer.py
pe_configurator-1.0.4.dist-info/LICENSE
pe_configurator-1.0.4.dist-info/METADATA
pe_configurator-1.0.4.dist-info/WHEEL
pe_configurator-1.0.4.dist-info/entry_points.txt
pe_configurator-1.0.4.dist-info/top_level.txt
pe_configurator-1.0.4.dist-info/RECORD
