Metadata-Version: 2.1
Name: pe-configurator
Version: 1.0.4
Summary: Tools to identify waveform settings and prior bounds for gravitational wave parameter estimation.
Author-email: Hector Estelles <hector.estelles@ligo.org>, Serguei Ossokine <serguei.ossokine@ligo.org>, Daniel Williams <daniel.williams@ligo.org>
License: MIT
Project-URL: Source code, https://git.ligo.org/pe/get_eob_settings
Classifier: Programming Language :: Python :: 3
Classifier: License :: OSI Approved :: MIT License
Classifier: Operating System :: OS Independent
Requires-Python: >=3.6
License-File: LICENSE
Requires-Dist: asimov >=0.4.0
Requires-Dist: lalsuite >=7.14
Requires-Dist: pandas
Requires-Dist: pesummary
Requires-Dist: nbformat
Requires-Dist: nbconvert
Requires-Dist: bilby
Requires-Dist: jupyter
Provides-Extra: asimov
Requires-Dist: asimov >=0.4.0 ; extra == 'asimov'
Provides-Extra: docs
Requires-Dist: sphinx ; extra == 'docs'
